{
  "id": "mablu-s-dream",
  "wiki_path": "/wiki/Mablu%27s_Dream",
  "wiki_image_url": "https://ffxiv.consolegameswiki.com/mediawiki/images/5/55/Quest_Complete.png",
  "patch": "7.0",
  "title_en": "Mablu's Dream",
  "title": "ความฝันของมาบลู",
  "level": "90",
  "location": "Urqopacha(X:29.4,Y:17.0)",
  "npc_start": "Wuk Lamat",
  "dialogues": [
    {
      "character": "Mablu",
      "text_en": "We've been doing so well! Even Tobli would have to agree...",
      "text": "พวกเราทำได้ดีมากเลยล่ะค่ะ! ขนาดคุณโทบลีก็คงต้องยอมรับแน่ๆ..."
    },
    {
      "character": "Wuk Lamat",
      "text_en": "Before we get moving... You should be the one to hold this.",
      "text": "ก่อนที่เราจะไปกันต่อ... นายน่าจะเป็นคนเก็บเจ้านี่ไว้ดีกว่านะ"
    },
    {
      "character": "Wuk Lamat",
      "text_en": "With that, I suppose we should hop on the alpacas Mablu has so kindly provided...",
      "text": "ถ้าอย่างนั้น พวกเราก็ขึ้นขี่อัลปาก้าที่มาบลูอุตส่าห์เตรียมไว้ให้กันเถอะ..."
    },
    {
      "character": "Wuk Lamat",
      "text_en": "If I'm going to catch a wild alpaca after this, I can't be shying away from the tame ones. Not that I'm scared of them, you understand. Or their nasty, disgusting, foul-smelling spit...",
      "text": "ถ้าหลังจากนี้ฉันจะต้องไปจับอัลปาก้าป่าล่ะก็ จะมามัวกลัวตัวที่เชื่องๆ แบบนี้ไม่ได้เด็ดขาด ไม่ใช่ว่าฉันกลัวพวกมันหรอกนะ เข้าใจใช่ไหม? หรือกลัวน้ำลายเหนียวเหนอะหนะ ส่งกลิ่นเหม็นโชยชวนแหวะนั่นด้วย..."
    },
    {
      "character": "Mablu",
      "text_en": "Ready to go? Let's mount up!",
      "text": "พร้อมจะลุยกันหรือยังคะ? ขึ้นขี่กันเลยค่ะ!"
    },
    {
      "character": "Mablu",
      "text_en": "And it's off to the mate fields we go!",
      "text": "งั้นมุ่งหน้าสู่สวนชาเมทกันเลยค่ะ!"
    },
    {
      "character": "Wuk Lamat",
      "text_en": "Please don't spit, please don't spit...",
      "text": "ขอร้องล่ะ อย่าพ่นน้ำลายใส่เลยนะ อย่าพ่นนะ..."
    },
    {
      "character": "Mablu",
      "text_en": "You'll be fine! These ones are accustomed to people!",
      "text": "ไม่เป็นไรหรอกค่ะ! เจ้าพวกนี้คุ้นเคยกับคนจะตายไป!"
    },
    {
      "character": "Wuk Lamat",
      "text_en": "I still don't trust them...",
      "text": "แต่ฉันก็ยังไม่ไว้ใจพวกมันอยู่ดีนั่นแหละ..."
    },
    {
      "character": "Mablu",
      "text_en": "You have a knack for riding, no matter what you say!",
      "text": "ถึงท่านจะพูดอย่างนั้น แต่ท่านก็ขี่เก่งใช่ย่อยเลยนะคะเนี่ย!"
    },
    {
      "character": "Mablu",
      "text_en": "Without our alpaca friends, we Pelu would never have become traveling merchants. Can you imagine walking all the way across Tural?",
      "text": "ถ้าไม่มีเพื่อนยากอย่างพวกอัลปาก้าล่ะก็ ชาวเปลูอย่างพวกเราคงไม่มีวันได้เป็นพ่อค้าเร่หรอกค่ะ ลองนึกภาพที่ต้องเดินเท้าตระเวนไปทั่วทั้งทูรัลดูสิคะ"
    },
    {
      "character": "Wuk Lamat",
      "text_en": "I swear, that mountain is too tall to be real.",
      "text": "ให้ตายสิ ภูเขาลูกนั้นมันสูงใหญ่เกินจริงชะมัดเลย"
    },
    {
      "character": "Wuk Lamat",
      "text_en": "Worqor Zormor... Wasn't that the name?",
      "text": "วอร์คอร์ ซอร์มอร์... ชื่อนี้ใช่ไหมนะ?"
    },
    {
      "character": "Mablu",
      "text_en": "A forbidding sight, isn't it? One I've never appreciated up close.",
      "text": "ดูน่าเกรงขามมากเลยใช่ไหมคะ? ฉันเองก็ยังไม่เคยขึ้นไปมองดูใกล้ๆ เลยสักครั้งเหมือนกันค่ะ"
    },
    {
      "character": "Mablu",
      "text_en": "You have to take the long way around the cliffs to get there─to the highlands belonging to the Yok Huy.",
      "text": "ถ้าจะไปที่นั่น ต้องเดินอ้อมหน้าผาไปไกลมากเลยล่ะค่ะ─ซึ่งนั่นเป็นเขตพื้นที่สูงของพวกยอคฮุยเขาน่ะ"
    },
    {
      "character": "Wuk Lamat",
      "text_en": "So, Mablu, you said you were learning about the peddler profession. You don't care for ranch work?",
      "text": "จริงด้วยสิ มาบลู เธอเคยบอกว่ากำลังเรียนรู้เรื่องการเป็นพ่อค้าเร่อยู่ใช่ไหม? แล้วเธอไม่ชอบงานในฟาร์มบ้างเหรอ?"
    },
    {
      "character": "Mablu",
      "text_en": "No, no, I love it! I love working with alpacas!",
      "text": "เปล่าเลยค่ะ ฉันรักงานฟาร์มจะตาย! แล้วก็ชอบคลุกคลีกับพวกอัลปาก้ามากๆ ด้วย!"
    },
    {
      "character": "Mablu",
      "text_en": "But becoming a peddler has always been a dream of mine.",
      "text": "แต่การได้เป็นพ่อค้าเร่เดินทางไปทั่วน่ะ มันเป็นความฝันของฉันมาโดยตลอดเลยล่ะค่ะ"
    },
    {
      "character": "Mablu",
      "text_en": "It's just... I'm not sure I have the talent for it.",
      "text": "เพียงแต่... ฉันก็ไม่ค่อยแน่ใจเหมือนกันว่าตัวเองจะมีพรสวรรค์พอหรือเปล่า"
    },
    {
      "character": "Mablu",
      "text_en": "If I can help you buy the taming saddle, though, then it'd be proof that I can do this after all.",
      "text": "แต่ถ้าฉันสามารถช่วยท่านสัญญาที่สามซื้ออานปราบสัตว์มาได้สำเร็จ นั่นก็จะเป็นข้อพิสูจน์ว่าฉันเองก็สามารถทำมันได้เหมือนกัน!"
    },
    {
      "character": "Wuk Lamat",
      "text_en": "In that case, you'd best get ready to be a merchant!",
      "text": "ถ้าอย่างนั้น เธอก็เตรียมตัวเป็นแม่ค้าเต็มตัวได้เลย!"
    },
    {
      "character": "Mablu",
      "text_en": "Look, we're almost there!",
      "text": "ดูนู่นสิคะ ใกล้จะถึงแล้ว!"
    },
    {
      "character": "Wuk Lamat",
      "text_en": "We made it...and without a single smelly incident.",
      "text": "ในที่สุดก็ถึงซะที... แถมยังไม่โดนพ่นน้ำลายใส่เลยสักแหมะ"
    },
    {
      "character": "Mablu",
      "text_en": "I sent the alpacas back to Icuvlo's Inn, so we'll walk along the main road when we return to the village.",
      "text": "ฉันส่งพวกอัลปาก้ากลับไปที่โรงเตี๊ยมไอคุฟโลแล้วค่ะ ขากลับเข้าหมู่บ้านพวกเราค่อยเดินเลาะไปตามถนนสายหลักกันนะคะ"
    },
    {
      "character": "Mablu",
      "text_en": "Speaking of roads to travel... You were adopted by the Dawnservant, weren't you, Third Promise?",
      "text": "พูดถึงเรื่องเส้นทางชีวิต... ท่านสัญญาที่สามถูกรับเลี้ยงโดยดอว์นเซิร์ฟวันต์ใช่ไหมคะ?"
    },
    {
      "character": "Wuk Lamat",
      "text_en": "That I was.",
      "text": "ใช่แล้วล่ะ"
    },
    {
      "character": "Mablu",
      "text_en": "Then perhaps you understand. I was an orphan too, you see─Tobli took me in. He took in all the ranch hands, actually.",
      "text": "ถ้าอย่างนั้นท่านก็น่าจะเข้าใจความรู้สึกดีเลยล่ะค่ะ เพราะตัวฉันเองก็เป็นเด็กกำพร้าเหมือนกัน─คุณโทบลีเป็นคนรับฉันมาเลี้ยงดู จริงๆ แล้วคนงานในฟาร์มทุกคนเขาก็รับมาชุบเลี้ยงหมดเลยล่ะค่ะ"
    },
    {
      "character": "Wuk Lamat",
      "text_en": "All of them?",
      "text": "ทุกคนเลยเหรอ?"
    },
    {
      "character": "Mablu",
      "text_en": "Yes, and everyone works hard at their chores, grateful for the opportunity to repay the head ledger's generosity. Yet here I am, the only one wanting to go off and be a merchant...",
      "text": "ใช่ค่ะ ทุกคนเลยขยันขันแข็งช่วยกันทำงานฟาร์มเพื่อทดแทนบุญคุณความเมตตาของคุณหัวหน้ากลุ่มพ่อค้า แต่ทว่าตัวฉัน... กลับเป็นคนเดียวที่อยากจะออกไปจากที่นี่เพื่อเป็นแม่ค้าเร่ซะอย่างนั้น..."
    },
    {
      "character": "Mablu",
      "text_en": "I'm sorry, I don't know why I'm telling you this! We need to keep trading things for your saddle if you're to prepare for the Feat of Gold.",
      "text": "ขอโทษด้วยนะคะ ไม่รู้ทำไมฉันถึงเล่าเรื่องนี้ขึ้นมาซะได้! ตอนนี้เราต้องมุ่งสมาธิไปกับการแลกเปลี่ยนของเพื่อนำไปแลกอานม้าให้ท่านสัญญาที่สามเตรียมพร้อมรับบททดสอบทองคำก่อนค่ะ"
    },
    {
      "character": "Mablu",
      "text_en": "As it's mate harvesting season, they can't have too many quality hatchets. Add to that Wuk Lamat's way with people, and we should have no trouble making a favorable deal.",
      "text": "เนื่องจากตอนนี้เป็นช่วงฤดูเก็บเกี่ยวชาเมท ขวานสั้นคุณภาพดีจึงเป็นที่ต้องการอย่างมากค่ะ ยิ่งบวกกับความสามารถในการเข้าหาคนของท่านวุค ลามัต แล้วล่ะก็ การเจรจาน่าจะได้ผลลัพธ์ที่ยอดเยี่ยมแน่นอนค่ะ"
    },
    {
      "character": "Mablu",
      "text_en": "That's Miplu herself over there! Pass the hatchet to the Third Promise, and let's get to bargaining!",
      "text": "นั่นไงคะ คุณมิพลูยืนอยู่ตรงนั้นเอง! ส่งขวานสั้นให้ท่านสัญญาที่สาม แล้วเราเข้าไปต่อรองกันเลยค่ะ!"
    },
    {
      "character": "Mablu",
      "text_en": "Did you give the hatchet back to Wuk Lamat? We should let her do the talking.",
      "text": "ส่งขวานสั้นคืนให้ท่านวุค ลามัต หรือยังคะ? ปล่อยให้ท่านเป็นคนเจรจาเถอะค่ะ"
    },
    {
      "character": "Miplu",
      "text_en": "To what do I owe this honor...?",
      "text": "ลมอะไรหอบมาถึงที่นี่กันล่ะคะเนี่ย...?"
    },
    {
      "character": "Wuk Lamat",
      "text_en": "You have that little axe for me?",
      "text": "ขวานด้ามสั้นเล่มนั้นอยู่กับนายรึเปล่า?"
    },
    {
      "character": "Wuk Lamat",
      "text_en": "Thanks! Now to see what we can get for it...",
      "text": "ขอบใจนะ! ทีนี้มาดูกันซิว่าเราจะแลกอะไรกลับมาได้บ้าง..."
    },
    {
      "character": "Wuk Lamat",
      "text_en": "You're Miplu, the owner of these fields? I have a mind to trade, if you're interested.",
      "text": "เธอคือมิพลู เจ้าของสวนแห่งนี้ใช่ไหม? ฉันอยากจะยื่นข้อเสนอแลกเปลี่ยนค้าขายด้วยสักหน่อย ถ้าเกิดเธอสนใจนะ"
    },
    {
      "character": "Miplu",
      "text_en": "Well, well, the Third Promise! I might be convinced to entertain a proposal. What do you have on offer?",
      "text": "โอ้โห ท่านสัญญาที่สามนี่เอง! ข้าอาจจะยอมรับฟังข้อเสนอดูก็ได้นะคะ แล้วท่านมีอะไรมานำเสนอสู้ล่ะคะ?"
    },
    {
      "character": "Wuk Lamat",
      "text_en": "This hatchet! Forged by a seasoned artisan, the razor edge of this exceptional tool will make light work of your crops!",
      "text": "นี่ไง ขวานสั้นเล่มนี้! ตีขึ้นรูปโดยช่างฝีมือผู้ช่ำชอง ใบมีดคมกริบของเครื่องมือชั้นเลิศนี้จะช่วยให้งานเก็บเกี่ยวพืชผลของเธอเป็นเรื่องกล้วยๆ เลยล่ะ!"
    },
    {
      "character": "Miplu",
      "text_en": "Hrm... The quality is acceptable, I suppose. I offer you a large sack of mate leaves in exchange.",
      "text": "หืม... คุณภาพนับว่าใช้ได้ทีเดียวนะคะ ถ้างั้นข้าขอเสนอแลกกับชาเมทถุงใหญ่หนึ่งกระสอบเป็นอย่างไรล่ะคะ"
    },
    {
      "character": "Mablu",
      "text_en": "A sack of mate leaves is valued at one pel in the thousands column─the same price as the hatchet. This deal would bring us no closer to the mezcal...",
      "text": "ชาเมทหนึ่งกระสอบมีมูลค่าเทียบเท่ากับหนึ่งเปลในระดับหลักพันค่ะ ซึ่งเป็นราคาเดียวกับมูลค่าของขวานสั้นเลย การแลกเปลี่ยนแบบนี้ไม่ได้ช่วยให้เราขยับเข้าใกล้เหล้าเมสคัลเลยนะคะ..."
    },
    {
      "character": "Mablu",
      "text_en": "If I may, Mistress Miplu. It's harvesting season, is it not? Does not the demand for hatchets afford them a higher value?",
      "text": "ขออนุญาตนะคะคุณมิพลู ช่วงนี้เป็นฤดูเก็บเกี่ยวไม่ใช่เหรอคะ? ความต้องการขวานสั้นก็น่าจะทำให้มันมีมูลค่าสูงขึ้นกว่าปกติสิคะ?"
    },
    {
      "character": "Miplu",
      "text_en": "It is indeed the season. Which is why I procured an ample batch of tools well in advance.",
      "text": "มันเป็นช่วงฤดูเก็บเกี่ยวจริงๆ นั่นแหละค่ะ ด้วยเหตุนี้ข้าถึงได้จัดเตรียมเครื่องมือเอาไว้ล่วงหน้าตั้งมากมายแล้วยังไงล่ะคะ"
    },
    {
      "character": "Mablu",
      "text_en": "We've missed the window for demand... In that case, we'll have to fall back on connections.",
      "text": "พวกเราช้าไปก้าวหนึ่งสินะคะ... ถ้าเป็นอย่างนั้น ก็ต้องหันมาใช้สายสัมพันธ์ส่วนตัวแล้วล่ะค่ะ"
    },
    {
      "character": "Mablu",
      "text_en": "Think of it this way! A generous deal here will put you in the Third Promise's good graces. Surely that's worthy of consideration?",
      "text": "ลองคิดดูแบบนี้สิคะ! หากยอมตกลงดีลพิเศษให้ในครั้งนี้ ก็จะสร้างความประทับใจที่ดีต่อท่านสัญญาที่สามด้วยนะคะ แบบนี้น่าสนใจพิจารณาไหมคะ?"
    },
    {
      "character": "Miplu",
      "text_en": "I do not wish to give offense, but I must tell you that I stand with the Second Promise. His innovations will improve every aspect of our lives, I believe─including farming. And I will no longer have need of hatchets.",
      "text": "ข้าก็ไม่ได้อยากจะทำให้ท่านเสียความรู้สึกหรอกนะคะ แต่ต้องบอกตรงๆ ว่าข้าเลือกสนับสนุนท่านสัญญาที่สองค่ะ นวัตกรรมและแนวคิดปฏิรูปของท่านจะช่วยพัฒนาทุกๆ ด้านในชีวิตของพวกเรา รวมถึงการเกษตรด้วย และในอนาคตข้าก็คงไม่มีความจำเป็นต้องใช้ขวานสั้นพวกนี้อีกแล้วล่ะค่ะ"
    },
    {
      "character": "Miplu",
      "text_en": "I assure you that I have nothing but respect for Wuk Lamat. That is why I'm prepared to purchase a spare hatchet at a fair price.",
      "text": "ข้ายืนยันได้เลยนะคะว่าข้าเคารพและนับถือในตัวท่านวุค ลามัต อย่างแท้จริง นั่นจึงเป็นเหตุผลที่ข้ายินดีจะรับซื้อขวานสั้นสำรองเล่มนี้ไว้ในราคาที่ยุติธรรมค่ะ"
    },
    {
      "character": "Mablu",
      "text_en": "I-I suppose it is fair given your reasons. But we ourselves would be no better off for the transaction...",
      "text": "ชะ... ฉันเข้าใจเหตุผลค่ะว่ามันก็เป็นราคาที่สมเหตุสมผลดีแล้ว แต่การตกลงแบบนี้มันไม่ได้ช่วยเพิ่มมูลค่าสินค้าของพวกเราเลยนี่คะ..."
    },
    {
      "character": "Wuk Lamat",
      "text_en": "How about this, then. If we were to help bring in your harvest, would you give us a better deal?",
      "text": "ถ้าอย่างนั้นเอาแบบนี้เป็นไง ถ้าพวกเราลงไปช่วยเก็บเกี่ยวผลผลิตในสวนของเธอด้วยล่ะ เธอจะให้ราคาพิเศษกับพวกเราขึ้นอีกได้ไหม?"
    },
    {
      "character": "Miplu",
      "text_en": "As a matter of fact, I would! Until Koana's reforms come about, I can always use more hands in the fields.",
      "text": "ถ้าเป็นแบบนั้นก็ย่อมได้สิคะ! กว่าจะถึงเวลาที่การปฏิรูปของท่านโคอานาจะมาถึง ข้าก็ยังต้องการแรงงานในฟาร์มอยู่เสมอค่ะ"
    },
    {
      "character": "Wuk Lamat",
      "text_en": "Then you can go ahead and add our labor to the bargain!",
      "text": "ถ้างั้นก็ตกลงตามนี้เลย! บวกค่าแรงของพวกเราเข้าไปในดีลแลกเปลี่ยนได้เลย!"
    },
    {
      "character": "Mablu",
      "text_en": "Added value to tip the scales... How could I have forgotten one of the most basic rules of trading?",
      "text": "การเพิ่มมูลค่าเพื่อถ่วงดุลราคา... นี่ฉันลืมกฎพื้นฐานที่สุดของการค้าขายไปได้ยังไงกันนะ?"
    },
    {
      "character": "Wuk Lamat",
      "text_en": "You can rest here if you like, Mablu. Forename and I have mate to gather!",
      "text": "เธอนั่งพักรอตรงนี้แหละ มาบลู เดี๋ยวฉันกับ Forename จะไปช่วยกันเก็บชาเมทให้เอง!"
    },
    {
      "character": "Mablu",
      "text_en": "Oh no, I'm helping too!",
      "text": "ไม่ได้หรอกค่ะ ฉันจะไปช่วยด้วย!"
    },
    {
      "character": "Miplu",
      "text_en": "Off to the fields, then, and mind you pick the healthy leaves. I'll take five good bundles from each of you.",
      "text": "ถ้าอย่างนั้นก็ลงมือกันได้เลยค่ะ คอยระวังเลือกเก็บเฉพาะใบที่สดสมบูรณ์ด้วยนะคะ ข้าขอรับส่วนแบ่งเป็นใบชาเมทคัดเกรดอย่างดีคนละห้ามัดค่ะ"
    },
    {
      "character": "Miplu",
      "text_en": "Isn't it splendid? Go ahead—drink in the verdant vista of my beautiful mate garden.",
      "text": "มันช่างงดงามเหลือเกินใช่ไหมล่ะคะ? เชิญชมทัศนียภาพอันเขียวขจีของไร่ชาเมทแสนรักของข้าได้ตามสบายเลยค่ะ"
    },
    {
      "character": "Wuk Lamat",
      "text_en": "I wasn't sure Miplu would bite, but it goes to show that you never know until you try!",
      "text": "ตอนแรกฉันก็แอบกังวลว่ามิพลูจะไม่ยอมรับข้อเสนอซะแล้ว แต่เรื่องนี้ทำให้เห็นเลยนะว่าถ้าไม่ลองพยายามดูก็ไม่มีวันรู้หรอก!"
    },
    {
      "character": "Mablu",
      "text_en": "Did you see how Wuk Lamat came to my rescue there? She really is good with people...",
      "text": "เห็นเมื่อกี้นี้ไหมคะที่ท่านวุค ลามัต เข้ามาช่วยกู้สถานการณ์ไว้ได้ทันเวลาพอดีเลย? ท่านเข้าหาผู้คนเก่งและมีวิธีพูดที่ยอดเยี่ยมจริงๆ ค่ะ..."
    },
    {
      "character": "Miplu",
      "text_en": "You've brought me some leaves, then?",
      "text": "เก็บใบชามาให้ข้าเรียบร้อยแล้วใช่ไหมคะ?"
    },
    {
      "character": "Miplu",
      "text_en": "An acceptable harvest. We'll see how your companions fared before I make any decisions, though.",
      "text": "ยอมรับเก็บเกี่ยวนับว่าใช้ได้นะคะ แต่ยังไงข้าคงต้องขอดูผลงานของสหายท่านที่เหลือด้วยก่อนตัดสินใจขั้นสุดท้ายนะคะ"
    },
    {
      "character": "Wuk Lamat",
      "text_en": "Here, we've brought our share as well.",
      "text": "นี่จ้ะ ส่วนของพวกเราก็เอามาให้แล้วเหมือนกัน"
    },
    {
      "character": "Miplu",
      "text_en": "Thank you, Third Promise. This is more than enough to hold up your end of the bargain.",
      "text": "ขอบคุณมากค่ะท่านสัญญาที่สาม ผลงานนี้มีมูลค่ามากเกินพอที่จะชดเชยค่าแรงตามข้อตกลงแล้วล่ะค่ะ"
    },
    {
      "character": "Miplu",
      "text_en": "Now it's time to honor mine. After adding the value of your labor to the price of the hatchet...",
      "text": "คราวนี้ถึงคราวที่ข้าต้องทำตามสัญญารักษาสัจจะบ้างแล้วล่ะค่ะ เมื่อคำนวณบวกมูลค่าจากแรงงานของพวกท่านเข้ากับราคาของขวานสั้นเล่มนั้นแล้ว..."
    },
    {
      "character": "Miplu",
      "text_en": "I am prepared to offer you a full sack of our highest-grade mate leaves!",
      "text": "ข้ายินดีที่จะขอมอบใบชาเมทเกรดพรีเมียมสูงสุดให้ท่านแบบเต็มกระสอบเลยค่ะ!"
    },
    {
      "character": "Mablu",
      "text_en": "Premium mate! Bought at the shop, one sack of those leaves would cost no less than five pel in the thousands column!",
      "text": "ชาเมทเกรดพรีเมียมงั้นเหรอคะ! ถ้าไปซื้อที่ร้านค้าตรงๆ กระสอบนี้มีมูลค่าไม่ต่ำกว่าห้าเปลในระดับหลักพันเลยนะคะ!"
    },
    {
      "character": "Wuk Lamat",
      "text_en": "Then we can bid farewell to this hatchet.",
      "text": "ถ้าอย่างนั้นก็ถึงเวลาบ๊ายบายเจ้าขวานสั้นเล่มนี้แล้วล่ะนะ"
    },
    {
      "character": "Miplu",
      "text_en": "I'll give it a good home. Talk of the contest aside, I'm glad we could come to a mutually agreeable trade.",
      "text": "ข้าจะดูแลรักษามันอย่างดีเลยค่ะ ไม่ว่าจะเรื่องประลองชิงบัลลังก์หรือไม่ ข้าก็รู้สึกยินดีมากๆ ที่เราตกลงเจรจาแลกเปลี่ยนค้าขายที่พึงพอใจกันทั้งสองฝ่ายได้ในครั้งนี้นะคะ"
    },
    {
      "character": "Wuk Lamat",
      "text_en": "As am I! All the best with the rest of your harvest!",
      "text": "ฉันก็เหมือนกัน! ขอให้การเก็บเกี่ยวที่เหลือราบรื่นไปด้วยดีนะ!"
    },
    {
      "character": "Wuk Lamat",
      "text_en": "Mablu? What's wrong?",
      "text": "มาบลู? เป็นอะไรไปเหรอ?"
    },
    {
      "character": "Mablu",
      "text_en": "It's as I was saying before... Even after everything Tobli's done for me, I'm planning to abandon it all and become a merchant.",
      "text": "ก็เรื่องที่ฉันเพิ่งเล่าไปเมื่อกี้นั่นแหละค่ะ... ทั้งที่ได้คุณโทบลีคอยชุบเลี้ยงอบรมช่วยเหลือมาตลอด แต่ฉันกลับคิดจะละทิ้งไร่แห่งนี้เพื่อไปประกอบอาชีพเป็นแม่ค้าเร่"
    },
    {
      "character": "Mablu",
      "text_en": "But then I needed your help after forgetting a basic rule of trade. How can I expect Tobli to accept my decision then...?",
      "text": "ขนาดแค่การค้าขายเล็กๆ เมื่อกี้ ฉันยังลืมกฎพื้นฐานจนต้องให้ท่านเข้ามาช่วยประคองสถานการณ์เลย แล้วแบบนี้ฉันจะกล้าหวังให้คุณโทบลียอมรับในการตัดสินใจของฉันได้ยังไงกันคะ..."
    },
    {
      "character": "Mablu",
      "text_en": "Not exactly. I wanted to prove I could succeed as a peddler before I declared my intentions...",
      "text": "ไม่เชิงหรอกค่ะ... ฉันแค่ตั้งใจว่าจะพิสูจน์ตัวเองให้เห็นว่าสามารถเป็นแม่ค้าเร่ที่ประสบความสำเร็จได้ก่อนที่จะบอกความจริงเรื่องความต้องการของตัวเองน่ะค่ะ..."
    },
    {
      "character": "Mablu",
      "text_en": "I can't! After getting a taste of real trading, I want to be a merchant more than ever!",
      "text": "มันทำไม่ได้หรอกค่ะ! ยิ่งได้สัมผัสรสชาติของการค้าขายจริงๆ แบบนี้ ความปรารถนาอยากจะเป็นแม่ค้าก็ยิ่งเอ่อล้นมากขึ้นกว่าเดิมหลายเท่าเลย!"
    },
    {
      "character": "Wuk Lamat",
      "text_en": "Then you'll just have to be honest.",
      "text": "ถ้าเป็นแบบนั้น เธอก็แค่ต้องพูดความจริงออกไปตรงๆ เท่านั้นแหละ"
    },
    {
      "character": "Wuk Lamat",
      "text_en": "I seek to follow in my father's footsteps, but not because he expects it of me. I want to preserve Tural's peace, and becoming Dawnservant happens to be the best way to do it.",
      "text": "ที่ฉันต้องการเดินตามรอยเท้าของท่านพ่อ ไม่ใช่เพราะเขามาคาดหวังหรือบังคับฉันหรอกนะ แต่เป็นเพราะตัวฉันเองที่ต้องการจะรักษาความสงบสุขของทูรัลเอาไว้ และการได้ขึ้นครองตำแหน่งดอว์นเซิร์ฟวันต์มันเป็นหนทางที่ดีที่สุดที่จะทำแบบนั้นได้ต่างหาก"
    },
    {
      "character": "Wuk Lamat",
      "text_en": "You should live a life of your own choosing, and I wouldn't be surprised if Tobli held the same opinion. So talk to him.",
      "text": "เธอควรจะได้ใช้ชีวิตในเส้นทางที่เธอเลือกเองนะ และฉันเชื่อว่าคุณโทบลีเองก็คงจะคิดแบบเดียวกันแน่นอน เพราะงั้น ลองไปคุยกับเขาดูตรงๆ เถอะ"
    },
    {
      "character": "Mablu",
      "text_en": "...You're right! It's better to find out for sure than worry over what he might say! Thank you for the advice.",
      "text": "...นั่นสิคะท่านวุค ลามัต! การไปคุยเพื่อหาคำตอบให้ชัดเจน ย่อมดีกว่าการมามัวนั่งฟุ้งซ่านกังวลว่าเขาจะพูดว่าอะไรตั้งเยอะ! ขอบคุณสำหรับคำแนะนำดีๆ นะคะ"
    },
    {
      "character": "Mablu",
      "text_en": "But first, we have a saddle to buy. I want that success under my belt so I can be sure of my decision!",
      "text": "แต่ก่อนอื่นเลย เรายังมีอานม้าที่ต้องไปจัดหามาให้ได้ค่ะ! ฉันอยากจะคว้าความสำเร็จนี้มาครองให้ได้ก่อน เพื่อสร้างความมั่นใจในการเลือกเส้นทางของตัวเองค่ะ!"
    },
    {
      "character": "Wuk Lamat",
      "text_en": "What's next, then? We try to trade our tea leaves for something halfway to ten thousand pel?",
      "text": "งั้นคราวนี้เราจะเอาไงต่อดีล่ะ? ลองเอาใบชาเมทพวกนี้ไปเสนอแลกกับของที่มีมูลค่าสักครึ่งทางของหมื่นเปลดีไหม?"
    },
    {
      "character": "Mablu",
      "text_en": "No, I think we're close enough now. I say we go straight for the premium mezcal!",
      "text": "ไม่ค่ะ ฉันคิดว่ามูลค่าตอนนี้ใกล้เคียงพอแล้วล่ะค่ะ! เราไปดีลแลกเหล้าเมสคัลเกรดพรีเมียมกันตรงๆ เลยดีกว่า!"
    },
    {
      "character": "Wuk Lamat",
      "text_en": "Bargain our way into double the value, eh? Think you can do it?",
      "text": "โอ้โห จะข้ามขั้นเพิ่มมูลค่าอีกเท่าตัวเลยเหรอ? คิดว่าไหวแน่นะ?"
    },
    {
      "character": "Mablu",
      "text_en": "Trust me! I will make this trade work!",
      "text": "เชื่อใจฉันได้เลยค่ะ! ฉันจะทำข้อตกลงนี้ให้สำเร็จให้ได้ค่ะ!"
    },
    {
      "character": "Mablu",
      "text_en": "I admire you, Third Promise. That you're holding your own against such strong competition for the throne is inspiring!",
      "text": "ฉันชื่นชมท่านสัญญาที่สามมากๆ เลยนะคะ การที่ท่านสามารถสู้ได้อย่างสมน้ำสมเนื้อกับคู่แข่งที่แข็งแกร่งขนาดนั้นในการชิงบัลลังก์ มันสร้างแรงบันดาลใจให้ฉันมากเลยค่ะ!"
    },
    {
      "character": "Wuk Lamat",
      "text_en": "Uh... Am I really holding my own against Koana and Zoraal Ja...?",
      "text": "เอ่อ... นี่ฉันสู้กับโคอานาแล้วก็โซราล จา ได้สมน้ำสมเนื้อจริงๆ อย่างนั้นเหรอ...?"
    },
    {
      "character": "Wuk Lamat",
      "text_en": "I-I mean, of course I am! I'm Wuk Lamat of the Dawn's Promise, after all!",
      "text": "จะ... เจ๊ย! หมายถึง แน่นอนอยู่แล้วสิ! ยังไงฉันก็คือวุค ลามัต ทายาทแห่งรุ่งอรุณเชียวนะ!"
    }
  ]
}