{
  "quest_id": "scales-of-blue",
  "dialogues": [
    {
      "key": "soweresupposedtogotoaplacecalledtruevueintheeasternsectorthisconveyoroughttotakeusthere",
      "text_en": "So, we're supposed to go to a place called True Vue, in the eastern sector. This conveyor ought to take us there.",
      "text": "สรุปคือเราต้องไปที่ทรู วิว ในเขตตะวันออกสินะ สายพานลำเลียงนี้น่าจะพาไปถึงที่นั่นได้"
    },
    {
      "key": "youknowonceyougetusedtoittheyreactuallykindoffuncomeonforename",
      "text_en": "You know, once you get used to it, they're actually kind of fun. Come on, Forename !",
      "text": "รู้ไหม พอคุ้นเคยแล้ว ก็น่าสนุกดีเหมือนกันนะ ตามมาเร็ว Forename !"
    },
    {
      "key": "thisistherightplaceyouthink",
      "text_en": "This is the right place, you think?",
      "text": "คิดว่ามาถูกที่แล้วใช่ไหม"
    },
    {
      "key": "idontseetheothersthough",
      "text_en": "I don't see the others, though...",
      "text": "แต่ยังไม่เห็นคนอื่นๆ เลยแฮะ..."
    },
    {
      "key": "wellratherthansittingandwaitingwemightaswellexploreabitmore",
      "text_en": "Well, rather than sitting and waiting, we might as well explore a bit more.",
      "text": "เอาเถอะ แทนที่จะนั่งรอเฉยๆ ออกไปสำรวจแถวนี้เพิ่มอีกหน่อยดีกว่า"
    },
    {
      "key": "huhforenamelookoverthere",
      "text_en": "Huh? Forename , look over there!",
      "text": "เอ๊ะ? ดูตรงนั้นสิ Forename !"
    },
    {
      "key": "amamooljachildwhataretheydoinghere",
      "text_en": "A Mamool Ja child... What are they doing here?",
      "text": "เด็กจากเผ่ามามูล จา... มาทำอะไรที่นี่กันนะ"
    },
    {
      "key": "younoticedtoorighttheresemblancetozoraalja",
      "text_en": "You noticed too, right? The resemblance to Zoraal Ja.",
      "text": "นายก็สังเกตเห็นเหมือนกันใช่ไหม ว่าช่างดูคล้ายโซราล จาเหลือเกิน"
    },
    {
      "key": "thebluescalesofaboonewawiththefeaturesofahoobigo",
      "text_en": "The blue scales of a Boonewa with the features of a Hoobigo...",
      "text": "เกล็ดสีน้ำเงินของชาวบูเนวาที่มีลักษณะหน้าตาของชาวฮูบิโก..."
    },
    {
      "key": "thiscantbeacoincidence",
      "text_en": "This can't be a coincidence.",
      "text": "เรื่องนี้ไม่มีทางเป็นเรื่องบังเอิญแน่"
    },
    {
      "key": "atanyrateitwouldntdotoleavesuchasmallchildontheirown",
      "text_en": "At any rate, it wouldn't do to leave such a small child on their own.",
      "text": "ยังไงซะ จะปล่อยเด็กตัวแค่นี้ไว้คนเดียวก็ไม่ดีแน่"
    },
    {
      "key": "comeonletsgoafterthem",
      "text_en": "Come on, let's go after them!",
      "text": "มาเถอะ รีบตามไปกันดีกว่า!"
    },
    {
      "key": "ithinktheyranthisway",
      "text_en": "I think they ran this way...",
      "text": "คิดว่าวิ่งมาทางนี้นะ..."
    },
    {
      "key": "sothisistruevueimnotsurewhatimlookingatbutitdoesseemlively",
      "text_en": "So this is True Vue. I'm not sure what I'm looking at, but it does seem lively!",
      "text": "ที่นี่น่ะหรือทรู วิว ถึงจะไม่ค่อยเข้าใจว่ากำลังมองอะไรอยู่ แต่ก็ดูครึกครื้นดีแฮะ!"
    },
    {
      "key": "thatbuildingsjustabouttheonlyonethatisntlitupnotopenforbusinessatthemomentiguess",
      "text_en": "That building's just about the only one that isn't lit up. Not open for business at the moment, I guess?",
      "text": "ตึกนั้นเป็นหลังเดียวที่ไม่เปิดไฟเลยแฮะ คงยังไม่เปิดร้านล่ะมั้ง?"
    },
    {
      "key": "uwaaah",
      "text_en": "Uwaaah!?",
      "text": "อุหวา!?"
    },
    {
      "key": "iididntseeyouthere",
      "text_en": "I-I didn't see you there...",
      "text": "ฉัน...ฉันไม่ทันเห็นเธอน่ะ"
    },
    {
      "key": "listenwedontmeanyouanyharmwejustwanttotalk",
      "text_en": "Listen, we don't mean you any harm. We just want to talk.",
      "text": "ฟังนะ พวกเราไม่ได้มาร้าย แค่อยากคุยด้วยเท่านั้นเอง"
    },
    {
      "key": "itsabitodddontyouthinktheyrunoffwhenweapproachonlytosuddenlyreappear",
      "text_en": "It's a bit odd, don't you think? They run off when we approach, only to suddenly reappear...",
      "text": "แปลกพิกลใช่ไหมล่ะ พอขยับเข้าไปใกล้ก็วิ่งหนี แล้วจู่ๆ ก็ผุดขึ้นมาซะอย่างนั้น..."
    },
    {
      "key": "coulditbetheywanttotakeussomewhere",
      "text_en": "Could it be they want to take us somewhere?",
      "text": "หรืออยากจะนำทางพวกเราไปที่ไหนสักแห่ง?"
    },
    {
      "key": "isthatthewayofityouwantustofollowyou",
      "text_en": "Is that the way of it? You want us to follow you?",
      "text": "อย่างนี้เองรึ อยากให้พวกเราตามไปสินะ"
    },
    {
      "key": "soitisalrightthenleadtheway",
      "text_en": "So it is! Alright, then, lead the way!",
      "text": "ใช่จริงๆ ด้วย! เอาละ นำทางไปเลย!"
    },
    {
      "key": "letsseewheretheytakeus",
      "text_en": "Let's see where they take us.",
      "text": "มาดูกันซิว่าจะพาไปที่ไหน"
    },
    {
      "key": "",
      "text_en": "...!",
      "text": "...!"
    },
    {
      "key": "letstrynottolosesightofthemthistime",
      "text_en": "Let's try not to lose sight of them this time!",
      "text": "คราวนี้อย่าให้คลาดสายตาเชียวนะ!"
    },
    {
      "key": "hmalexandrianfoodnotagreeingwithyourstomachalrightillletthelittleoneknowyouneedsometimewellwaitforyoubackwherewestarted",
      "text_en": "Hm? Alexandrian food not agreeing with your stomach? Alright, I'll let the little one know you need some time. We'll wait for you back where we started.",
      "text": "หือ? อาหารอเล็กซานเดรียทำพิษกับท้องไส้รึ เอาละ เดี๋ยวจะบอกเจ้าหนูให้ว่าขอเวลาสักหน่อย พวกเราจะกลับไปรอตรงจุดเริ่มต้นนะ"
    },
    {
      "key": "damnitwevelostthemprobablybesttoreturntowherewestarted",
      "text_en": "Damn it, we've lost them! Probably best to return to where we started...",
      "text": "ปัดโธ่เอ๊ย คลาดกันจนได้! คงต้องกลับไปตรงจุดเริ่มต้นก่อน..."
    },
    {
      "key": "",
      "text_en": "...!",
      "text": "...!"
    },
    {
      "key": "isthiswhereyouwantedtobringus",
      "text_en": "Is this where you wanted to bring us?",
      "text": "ที่นี่เองรึที่อยากพาพวกเรามา"
    },
    {
      "key": "whatisthisplaceifyouremeanttorelaxhereitisntworkingforme",
      "text_en": "What is this place? If you're meant to relax here, it isn't working for me...",
      "text": "ที่นี่มันที่ไหนกันเนี่ย ถ้าคิดจะให้พักผ่อนหย่อนใจละก็ สำหรับฉันไม่ได้ผลเลยสักนิด..."
    },
    {
      "key": "heywhatsyourname",
      "text_en": "Hey, what's your name?",
      "text": "นี่ เจ้าหนู ชื่ออะไรเหรอ"
    },
    {
      "key": "soyourestillnotinclinedtotalk",
      "text_en": "So you're still not inclined to talk...",
      "text": "ดูท่าจะยังไม่อยากคุยด้วยสินะ..."
    },
    {
      "key": "hellonlytalkifhescompletelycomfortablewithyou",
      "text_en": "He'll only talk if he's completely comfortable with you.",
      "text": "จะยอมพูดด้วยก็ต่อเมื่อรู้สึกคุ้นเคยจนไว้ใจเธอเต็มที่แล้วเท่านั้นแหละ"
    },
    {
      "key": "youknowhim",
      "text_en": "You know him?",
      "text": "รู้จักเจ้าหนูนี่ด้วยงั้นเหรอ"
    },
    {
      "key": "afterafashionbutnevermindthathowaboutsomethingtowetyourwhistle",
      "text_en": "After a fashion. But never mind that. How about something to wet your whistle?",
      "text": "ก็พอรู้จักอยู่บ้างแหละจ้ะ แต่ช่างเรื่องนั้นก่อนเถอะ รับอะไรดื่มแก้คอแห้งสักหน่อยไหมจ๊ะ"
    },
    {
      "key": "adorableasyouareitsonthehouseicanrecommendourspecialhermajestyillprepareonewithoutliquorfortheboytoo",
      "text_en": "Adorable as you are, it's on the house. I can recommend our special—Her Majesty. I'll prepare one without liquor for the boy, too.",
      "text": "เห็นแก่ความน่ารักของเธอ แก้วนี้พี่เลี้ยงเองจ้ะ ขอแนะนำสูตรพิเศษของร้าน—'เฮอร์ มาเจสตี้' เดี๋ยวจะเตรียมแบบไม่มีแอลกอฮอล์ให้เจ้าหนูด้วยนะ"
    },
    {
      "key": "uhthanksbutnothanksweresupposedtomeetafriendnamedcahciua",
      "text_en": "Uh, thanks, but no thanks. We're supposed to meet a friend named Cahciua.",
      "text": "เอ่อ ขอบคุณนะ แต่ไม่เป็นไรดีกว่า พวกเรามีนัดเจอกับเพื่อนที่ชื่อคาชิวาน่ะ"
    },
    {
      "key": "butweranintothechildonthewayandheledushere",
      "text_en": "But we ran into the child on the way, and he led us here.",
      "text": "แต่บังเอิญเจอเจ้าหนูนี่ระหว่างทาง ก็เลยนำทางพวกเรามาที่นี่"
    },
    {
      "key": "ohhhsoyourewithcahciua",
      "text_en": "Ohhh, so you're with Cahciua.",
      "text": "อ๋อ ที่แท้ก็เป็นพวกของคาชิวานี่เอง"
    },
    {
      "key": "inthatcasegoandhaveachatwithbigtassostherehellshowyoutoafunplace",
      "text_en": "In that case, go and have a chat with big Tassos there. He'll show you to a fun place.",
      "text": "ถ้าอย่างนั้นลองไปคุยกับพี่เบิ้มทัสซอสตรงโน้นดูสิ เดี๋ยวจะพาไปที่สนุกๆ เองจ้ะ"
    },
    {
      "key": "whatabouthim",
      "text_en": "What about him?",
      "text": "แล้วเด็กคนนี้ล่ะ"
    },
    {
      "key": "idontthinkhesinamoodtotalksohecantendthebarwithme",
      "text_en": "I don't think he's in a mood to talk, so he can tend the bar with me.",
      "text": "ดูท่าทางแกคงไม่อยากคุยด้วยเท่าไหร่ ให้ช่วยเฝ้าบาร์กับฉันที่นี่ก็แล้วกันนะ"
    },
    {
      "key": "thishastakenaturnforthestrangebutyoudontthinkwerewalkingintoatrapdoyou",
      "text_en": "This has taken a turn for the strange, but you don't think we're walking into a trap, do you?",
      "text": "เรื่องชักจะชอบกลขึ้นทุกที แกคงไม่คิดว่าพวกเรากำลังเดินเข้ากับดักหรอกนะ"
    },
    {
      "key": "damnedifthisdoesnthavesuspiciouswrittenalloverit",
      "text_en": "Damned if this doesn't have suspicious written all over it...",
      "text": "ให้ตายสิ ไม่ว่าจะมองมุมไหนก็ชวนสงสัยไปหมด..."
    },
    {
      "key": "ifyoufeellikethatdrinkafteralljustletmeknow",
      "text_en": "If you feel like that drink after all, just let me know.",
      "text": "ถ้าเปลี่ยนใจอยากดื่มขึ้นมาเมื่อไหร่ก็บอกฉันได้เลยนะ"
    },
    {
      "key": "",
      "text_en": "...",
      "text": "..."
    },
    {
      "key": "youseemeagertogobutwhataboutyourfriendthere",
      "text_en": "You seem eager to go, but what about your friend there?",
      "text": "ดูท่าทางคุณจะรีบร้อนเหลือเกิน แล้วเพื่อนของคุณคนนั้นล่ะ"
    },
    {
      "key": "whatisthisfunplacemeanttobeiscahciuathere",
      "text_en": "What is this “fun place” meant to be? Is Cahciua there?",
      "text": "“สถานที่แสนสนุก” ที่ว่านั่นมันคืออะไรกันแน่ คาห์ชิอัวอยู่ที่นั่นใช่ไหม"
    },
    {
      "key": "wellisupposetheresonlyonewaytofindout",
      "text_en": "Well, I suppose there's only one way to find out...",
      "text": "เอาเถอะ คงมีแค่หนทางเดียวที่จะรู้ได้..."
    }
  ]
}